uniswapV3Python/__init__.py
uniswapV3Python/src/UniswapPool.py
uniswapV3Python/src/__init__.py
uniswapV3Python/src/libraries/Account.py
uniswapV3Python/src/libraries/Factory.py
uniswapV3Python/src/libraries/FullMath.py
uniswapV3Python/src/libraries/LiquidityMath.py
uniswapV3Python/src/libraries/Position.py
uniswapV3Python/src/libraries/SafeMath.py
uniswapV3Python/src/libraries/Shared.py
uniswapV3Python/src/libraries/SqrtPriceMath.py
uniswapV3Python/src/libraries/SwapMath.py
uniswapV3Python/src/libraries/Tick.py
uniswapV3Python/src/libraries/TickMath.py
uniswapV3Python/src/libraries/__init__.py
uniswapV3Python/tests/UniswapV3PoolSwaps.py
uniswapV3Python/tests/__init__.py
uniswapV3Python/tests/poolFixtures.py
uniswapV3Python/tests/test_SqrtPriceMath.py
uniswapV3Python/tests/test_factory.py
uniswapV3Python/tests/test_swapMath.py
uniswapV3Python/tests/test_swaps.py
uniswapV3Python/tests/test_tick.py
uniswapV3Python/tests/test_tickMath.py
uniswapV3Python/tests/test_ticks.py
uniswapV3Python/tests/test_tokenTransfer.py
uniswapV3Python/tests/test_uniswapPool.py
uniswapV3Python/tests/utilities.py
uniswapV3Python-1.0.0.dist-info/LICENSE
uniswapV3Python-1.0.0.dist-info/METADATA
uniswapV3Python-1.0.0.dist-info/WHEEL
uniswapV3Python-1.0.0.dist-info/top_level.txt
uniswapV3Python-1.0.0.dist-info/RECORD
