Metadata-Version: 2.1
Name: uniswapV3Python
Version: 1.0.0
Summary: Pythonized Uniswap V3
Home-page: https://github.com/chainflip-io/python-uniswap-v3
Author: Chainflip Labs
Author-email: albert@chainflip.io
Classifier: Programming Language :: Python :: 3
Classifier: License :: OSI Approved :: MIT License
Classifier: Operating System :: OS Independent
Requires-Python: >=3.7
License-File: LICENSE
